bitmex_liquidation/__init__.py
bitmex_liquidation/api.py
bitmex_liquidation-1.0.1.dist-info/METADATA
bitmex_liquidation-1.0.1.dist-info/WHEEL
bitmex_liquidation-1.0.1.dist-info/top_level.txt
bitmex_liquidation-1.0.1.dist-info/RECORD
