Metadata-Version: 2.1
Name: bitmex-liquidation
Version: 1.0.1
Summary: BitMEX Liquidation Python Wrapper
Home-page: UNKNOWN
Author: Philippe Remy
License: MIT
Platform: UNKNOWN
Requires-Dist: websocket-client (==0.47.0)
